easy_blockchain/__init__.py
easy_blockchain/blockchain.py
easy_blockchain/blockchain_v2.py
easy_blockchain/database.py
easy_blockchain/testcoin.py
easy_blockchain/wallet.py
easy_blockchain-0.1.6.dist-info/DESCRIPTION.rst
easy_blockchain-0.1.6.dist-info/METADATA
easy_blockchain-0.1.6.dist-info/RECORD
easy_blockchain-0.1.6.dist-info/WHEEL
easy_blockchain-0.1.6.dist-info/metadata.json
easy_blockchain-0.1.6.dist-info/top_level.txt
pyblockchain/__init__.py
pyblockchain/blockchain.py
pyblockchain/database.py
pyblockchain/testcoin.py
pyblockchain/wallet.py
