Metadata-Version: 2.0
Name: easy-blockchain
Version: 0.1.6
Summary: A blockchain for human
Home-page: https://github.com/minhtuan221/py-blockchain
Author: Minh Tuan Nguyen
Author-email: ntuan221@gmail.com
License: BSD
Keywords: microservice,http,flask,ecdsa,blockchain
Platform: any
Classifier: Development Status :: 3 - Alpha
Classifier: License :: OSI Approved :: BSD License
Classifier: Environment :: Web Environment
Classifier: Operating System :: OS Independent
Classifier: Programming Language :: Python
Classifier: Programming Language :: Python :: 3.5
Classifier: Programming Language :: Python :: 3.6
Classifier: Topic :: Internet :: WWW/HTTP :: Dynamic Content
Classifier: Topic :: Internet :: WWW/HTTP :: WSGI :: Application
Classifier: Topic :: Software Development :: Libraries :: Application Frameworks
Classifier: Topic :: Software Development :: Libraries :: Python Modules
Requires-Dist: ecdsa
Requires-Dist: flask
Requires-Dist: requests
